topsis_yash_102303701/__init__.py
topsis_yash_102303701/topsis.py
topsis_yash_102303701-0.0.3.dist-info/METADATA
topsis_yash_102303701-0.0.3.dist-info/WHEEL
topsis_yash_102303701-0.0.3.dist-info/entry_points.txt
topsis_yash_102303701-0.0.3.dist-info/top_level.txt
topsis_yash_102303701-0.0.3.dist-info/RECORD
