Metadata-Version: 2.4
Name: TOPSIS-Yash-102303701
Version: 0.0.3
Summary: TOPSIS implementation using Python
Author: Yash Sharma
Author-email: yash@example.com
Requires-Dist: pandas
Requires-Dist: numpy
Dynamic: author
Dynamic: author-email
Dynamic: description
Dynamic: description-content-type
Dynamic: requires-dist
Dynamic: summary
